dataflows_normalize/VERSION
dataflows_normalize/__init__.py
dataflows_normalize/log.py
dataflows_normalize/normalize.py
dataflows_normalize-0.0.11.dist-info/LICENSE
dataflows_normalize-0.0.11.dist-info/METADATA
dataflows_normalize-0.0.11.dist-info/WHEEL
dataflows_normalize-0.0.11.dist-info/top_level.txt
dataflows_normalize-0.0.11.dist-info/RECORD
