Metadata-Version: 2.1
Name: dataflows-normalize
Version: 0.0.11
Summary: A resource normalizer for dataflows
Home-page: https://github.com/dataspot/dataflows-normalize
Author: Adam Kariv
Author-email: adam.kariv@gmail.com
License: MIT
Keywords: data
Platform: UNKNOWN
Classifier: Development Status :: 4 - Beta
Classifier: Intended Audience :: Developers
Classifier: License :: OSI Approved :: MIT License
Classifier: Operating System :: OS Independent
Classifier: Programming Language :: Python :: 3.6
Classifier: Programming Language :: Python :: 3.7
Classifier: Topic :: Software Development :: Libraries :: Python Modules
Requires-Dist: dataflows (>=0.0.51)
Requires-Dist: kvfile (>=0.0.7)
Requires-Dist: psycopg2-binary
Provides-Extra: develop
Requires-Dist: pylama ; extra == 'develop'
Requires-Dist: tox ; extra == 'develop'
